heligeo/__init__.py
heligeo/main.py
heligeo-1.1.10.dist-info/LICENSE
heligeo-1.1.10.dist-info/METADATA
heligeo-1.1.10.dist-info/WHEEL
heligeo-1.1.10.dist-info/top_level.txt
heligeo-1.1.10.dist-info/RECORD
