Metadata-Version: 2.1
Name: heligeo
Version: 1.1.10
Summary: Python client for requests to heligeo API services
Author: Heliware
Author-email: rajan@heliware.co.in
License: MIT
Platform: UNKNOWN
Classifier: License :: OSI Approved :: MIT License
Classifier: Programming Language :: Python :: 3.6
Classifier: Programming Language :: Python :: 3.7
Classifier: Programming Language :: Python :: 3.8
License-File: LICENSE
Requires-Dist: numpy
Requires-Dist: Shapely
Requires-Dist: plotly
Requires-Dist: requests
Requires-Dist: dash
Requires-Dist: pandas
Requires-Dist: dash-bootstrap-components
Requires-Dist: kml2geojson
Requires-Dist: geo2kml
Requires-Dist: ezdxf
Requires-Dist: pyshp
